<?xml version="1.0" encoding="utf-8" ?><dwsync><file name="000054810014.jpg" server="www.codehamilton.com//" local="3459597717" remote="323953104375852344" Dst="-1" /><file name="000011110020.jpg" server="www.codehamilton.com//" local="3459597718" remote="323953104375852344" Dst="-1" /><file name="000011120016.jpg" server="www.codehamilton.com//" local="3459597719" remote="323953104375852344" Dst="-1" /><file name="7755-036.jpg" server="www.codehamilton.com//" local="3459597719" remote="323953104375852344" Dst="-1" /><file name="35880016.jpg" server="www.codehamilton.com//" local="3459597716" remote="323953104375852344" Dst="-1" /><file name="7756-002.jpg" server="www.codehamilton.com//" local="3459597716" remote="323953104375852344" Dst="-1" /><file name="8942-001.jpg" server="www.codehamilton.com//" local="3459597704" remote="323953104375852344" Dst="-1" /><file name="8942-010.jpg" server="www.codehamilton.com//" local="3459597717" remote="323953104375852344" Dst="-1" /><file name="8942-013.jpg" server="www.codehamilton.com//" local="3459597718" remote="323953104375852344" Dst="-1" /><file name="sc000fa5fa.jpg" server="www.codehamilton.com//" local="3459597715" remote="323953104375852344" Dst="-1" /><file name="sc00023c15.jpg" server="www.codehamilton.com//" local="3459597717" remote="323953104375852344" Dst="-1" /><file name="000070840021.jpg" server="www.codehamilton.com//" local="3459597716" remote="323953104375852344" Dst="-1" /></dwsync>